[
    {
        "rank": "1",
        "name": "Kento YAMAGUCHI",
        "age": "2",
        "country": "JPN",
        "score": "4T4z 10 9",
        "routes": [
            {
                "route_number": "1",
                "tops": "1",
                "zones": "1"
            },
            {
                "route_number": "2",
                "tops": "2",
                "zones": "1"
            },
            {
                "route_number": "3",
                "tops": "4",
                "zones": "4"
            },
            {
                "route_number": "4",
                "tops": "3",
                "zones": "3"
            }
        ]
    },
    {
        "rank": "2",
        "name": "Ao YURIKUSA",
        "age": "3",
        "country": "JPN",
        "score": "3T4z 6 7",
        "routes": [
            {
                "route_number": "1",
                "tops": "2",
                "zones": "2"
            },
            {
                "route_number": "2",
                "tops": "",
                "zones": "2"
            },
            {
                "route_number": "3",
                "tops": "2",
                "zones": "1"
            },
            {
                "route_number": "4",
                "tops": "2",
                "zones": "2"
            }
        ]
    },
    {
        "rank": "3",
        "name": "Sohta AMAGASA",
        "age": "1",
        "country": "JPN",
        "score": "3T4z 7 7",
        "routes": [
            {
                "route_number": "1",
                "tops": "2",
                "zones": "1"
            },
            {
                "route_number": "2",
                "tops": "",
                "zones": "1"
            },
            {
                "route_number": "3",
                "tops": "2",
                "zones": "2"
            },
            {
                "route_number": "4",
                "tops": "3",
                "zones": "3"
            }
        ]
    },
    {
        "rank": "4",
        "name": "Ryo OMASA",
        "age": "22",
        "country": "JPN",
        "score": "2T4z 9 11",
        "routes": [
            {
                "route_number": "1",
                "tops": "2",
                "zones": "1"
            },
            {
                "route_number": "2",
                "tops": "",
                "zones": "2"
            },
            {
                "route_number": "3",
                "tops": "",
                "zones": "1"
            },
            {
                "route_number": "4",
                "tops": "7",
                "zones": "7"
            }
        ]
    },
    {
        "rank": "5",
        "name": "Taisei HOMMA",
        "age": "34",
        "country": "JPN",
        "score": "2T3z 6 7",
        "routes": [
            {
                "route_number": "1",
                "tops": "2",
                "zones": "1"
            },
            {
                "route_number": "2",
                "tops": "",
                "zones": "4"
            },
            {
                "route_number": "3",
                "tops": "",
                "zones": ""
            },
            {
                "route_number": "4",
                "tops": "4",
                "zones": "2"
            }
        ]
    },
    {
        "rank": "6",
        "name": "Maxim PARE",
        "age": "33",
        "country": "AUS",
        "score": "2T2z 6 4",
        "routes": [
            {
                "route_number": "1",
                "tops": "3",
                "zones": "2"
            },
            {
                "route_number": "2",
                "tops": "",
                "zones": ""
            },
            {
                "route_number": "3",
                "tops": "",
                "zones": ""
            },
            {
                "route_number": "4",
                "tops": "3",
                "zones": "2"
            }
        ]
    },
    {
        "rank": "7",
        "name": "Gabriel GALEN",
        "age": "38",
        "country": "USA",
        "score": "1T3z 2 11",
        "routes": [
            {
                "route_number": "1",
                "tops": "2",
                "zones": "1"
            },
            {
                "route_number": "2",
                "tops": "",
                "zones": "5"
            },
            {
                "route_number": "3",
                "tops": "",
                "zones": ""
            },
            {
                "route_number": "4",
                "tops": "",
                "zones": "5"
            }
        ]
    },
    {
        "rank": "8",
        "name": "Mikel Asier LINACISORO MOLINA",
        "age": "4",
        "country": "ESP",
        "score": "1T3z 2 14",
        "routes": [
            {
                "route_number": "1",
                "tops": "2",
                "zones": "1"
            },
            {
                "route_number": "2",
                "tops": "",
                "zones": "6"
            },
            {
                "route_number": "3",
                "tops": "",
                "zones": ""
            },
            {
                "route_number": "4",
                "tops": "",
                "zones": "7"
            }
        ]
    },
    {
        "rank": "9",
        "name": "Andoni ESPARTA FRADE",
        "age": "13",
        "country": "ESP",
        "score": "1T2z 3 7",
        "routes": [
            {
                "route_number": "1",
                "tops": "3",
                "zones": "1"
            },
            {
                "route_number": "2",
                "tops": "",
                "zones": ""
            },
            {
                "route_number": "3",
                "tops": "",
                "zones": ""
            },
            {
                "route_number": "4",
                "tops": "",
                "zones": "6"
            }
        ]
    },
    {
        "rank": "10",
        "name": "Matthias ERBER",
        "age": "17",
        "country": "AUT",
        "score": "1T2z 5 5",
        "routes": [
            {
                "route_number": "1",
                "tops": "",
                "zones": "1"
            },
            {
                "route_number": "2",
                "tops": "",
                "zones": ""
            },
            {
                "route_number": "3",
                "tops": "",
                "zones": ""
            },
            {
                "route_number": "4",
                "tops": "5",
                "zones": "4"
            }
        ]
    },
    {
        "rank": "11",
        "name": "Ben BLACKMORE",
        "age": "20",
        "country": "USA",
        "score": "0T3z 0 7",
        "routes": [
            {
                "route_number": "1",
                "tops": "",
                "zones": "1"
            },
            {
                "route_number": "2",
                "tops": "",
                "zones": "5"
            },
            {
                "route_number": "3",
                "tops": "",
                "zones": ""
            },
            {
                "route_number": "4",
                "tops": "",
                "zones": "1"
            }
        ]
    },
    {
        "rank": "12",
        "name": "Peter KURIC",
        "age": "10",
        "country": "SVK",
        "score": "0T3z 0 9",
        "routes": [
            {
                "route_number": "1",
                "tops": "",
                "zones": "1"
            },
            {
                "route_number": "2",
                "tops": "",
                "zones": "7"
            },
            {
                "route_number": "3",
                "tops": "",
                "zones": ""
            },
            {
                "route_number": "4",
                "tops": "",
                "zones": "1"
            }
        ]
    },
    {
        "rank": "13",
        "name": "Simon POTUCEK",
        "age": "36",
        "country": "CZE",
        "score": "0T3z 0 16",
        "routes": [
            {
                "route_number": "1",
                "tops": "",
                "zones": "6"
            },
            {
                "route_number": "2",
                "tops": "",
                "zones": "8"
            },
            {
                "route_number": "3",
                "tops": "",
                "zones": ""
            },
            {
                "route_number": "4",
                "tops": "",
                "zones": "2"
            }
        ]
    },
    {
        "rank": "14",
        "name": "Johannes EGGER",
        "age": "11",
        "country": "ITA",
        "score": "0T2z 0 2",
        "routes": [
            {
                "route_number": "1",
                "tops": "",
                "zones": "1"
            },
            {
                "route_number": "2",
                "tops": "",
                "zones": "1"
            },
            {
                "route_number": "3",
                "tops": "",
                "zones": ""
            },
            {
                "route_number": "4",
                "tops": "",
                "zones": ""
            }
        ]
    },
    {
        "rank": "15",
        "name": "Derek NEW",
        "age": "29",
        "country": "USA",
        "score": "0T2z 0 4",
        "routes": [
            {
                "route_number": "1",
                "tops": "",
                "zones": "1"
            },
            {
                "route_number": "2",
                "tops": "",
                "zones": "3"
            },
            {
                "route_number": "3",
                "tops": "",
                "zones": ""
            },
            {
                "route_number": "4",
                "tops": "",
                "zones": ""
            }
        ]
    },
    {
        "rank": "16",
        "name": "Donggun PARK",
        "age": "25",
        "country": "KOR",
        "score": "0T2z 0 6",
        "routes": [
            {
                "route_number": "1",
                "tops": "",
                "zones": "1"
            },
            {
                "route_number": "2",
                "tops": "",
                "zones": ""
            },
            {
                "route_number": "3",
                "tops": "",
                "zones": ""
            },
            {
                "route_number": "4",
                "tops": "",
                "zones": "5"
            }
        ]
    },
    {
        "rank": "17",
        "name": "Dimitri VOGT",
        "age": "16",
        "country": "SUI",
        "score": "0T2z 0 7",
        "routes": [
            {
                "route_number": "1",
                "tops": "",
                "zones": "3"
            },
            {
                "route_number": "2",
                "tops": "",
                "zones": ""
            },
            {
                "route_number": "3",
                "tops": "",
                "zones": ""
            },
            {
                "route_number": "4",
                "tops": "",
                "zones": "4"
            }
        ]
    },
    {
        "rank": "18",
        "name": "Stepan POTUCEK",
        "age": "6",
        "country": "CZE",
        "score": "0T2z 0 8",
        "routes": [
            {
                "route_number": "1",
                "tops": "",
                "zones": "3"
            },
            {
                "route_number": "2",
                "tops": "",
                "zones": ""
            },
            {
                "route_number": "3",
                "tops": "",
                "zones": ""
            },
            {
                "route_number": "4",
                "tops": "",
                "zones": "5"
            }
        ]
    },
    {
        "rank": "19",
        "name": "Olaf MALINOWSKI",
        "age": "37",
        "country": "POL",
        "score": "0T1z 0 1",
        "routes": [
            {
                "route_number": "1",
                "tops": "",
                "zones": "1"
            },
            {
                "route_number": "2",
                "tops": "",
                "zones": ""
            },
            {
                "route_number": "3",
                "tops": "",
                "zones": ""
            },
            {
                "route_number": "4",
                "tops": "",
                "zones": ""
            }
        ]
    },
    {
        "rank": "20",
        "name": "Aiden YANEV",
        "age": "40",
        "country": "AUS",
        "score": "0T0z 0 0",
        "routes": [
            {
                "route_number": "1",
                "tops": "",
                "zones": ""
            },
            {
                "route_number": "2",
                "tops": "",
                "zones": ""
            },
            {
                "route_number": "3",
                "tops": "",
                "zones": ""
            },
            {
                "route_number": "4",
                "tops": "",
                "zones": ""
            }
        ]
    }
]